<?xml version="1.0" encoding="utf-8" ?>
<dwsync>
<file name="clock backup.css" server="50.63.197.201" local="130435194160000000" remote="130523220600000000" Dst="2" />
<file name="cube.css" server="50.63.197.201" local="130463771098732542" remote="130523220600000000" Dst="2" />
<file name="minimal.css" server="50.63.197.201" local="130435207960000000" remote="130523220600000000" Dst="2" />
<file name="clock backup.css" server="ftp.ctpiinc.com" local="130435194160000000" remote="130536973200000000" Dst="2" />
<file name="minimal.css" server="ftp.ctpiinc.com" local="130572949870000000" remote="130572842400000000" Dst="2" />
<file name="cube.css" server="ftp.ctpiinc.com" local="130540148950000000" remote="130540040400000000" Dst="2" />
<file name="cubeProfile.css" server="ftp.ctpiinc.com" local="130555631538455862" remote="130555523400000000" Dst="2" />
<file name="clock backup.css" server="ftp.all-of.us" local="130435194160000000" remote="130927627800000000" Dst="1" />
<file name="cube.css" server="ftp.all-of.us" local="130540148953540445" remote="130927627800000000" Dst="1" />
<file name="cubeProfile.css" server="ftp.all-of.us" local="130555631530000000" remote="130927627800000000" Dst="1" />
<file name="minimal.css" server="ftp.all-of.us" local="130572949870000000" remote="130927627800000000" Dst="1" />
<file name="clock backup.css" server="ftp.allov.us" local="130435194160000000" remote="130927660800000000" Dst="1" />
<file name="cube.css" server="ftp.allov.us" local="130540148953540445" remote="130927660800000000" Dst="1" />
<file name="cubeProfile.css" server="ftp.allov.us" local="130555631530000000" remote="130927660800000000" Dst="1" />
<file name="minimal.css" server="ftp.allov.us" local="130572949870000000" remote="130927660800000000" Dst="1" />
</dwsync>